{
  "main": {
    "id": "e3b97df5e9043ea2",
    "type": "split",
    "children": [
      {
        "id": "e2e6283a4de5ee52",
        "type": "tabs",
        "children": [
          {
            "id": "694dc2f3cb983df4",
            "type": "leaf",
            "state": {
              "type": "markdown",
              "state": {
                "file": "运维相关/工具/SaltStack.md",
                "mode": "source",
                "source": false
              },
              "icon": "lucide-file",
              "title": "SaltStack"
            }
          }
        ]
      }
    ],
    "direction": "vertical"
  },
  "left": {
    "id": "15efdc66f1ebc9b2",
    "type": "split",
    "children": [
      {
        "id": "3218089d01c1d4ac",
        "type": "tabs",
        "children": [
          {
            "id": "31e62439d44a2651",
            "type": "leaf",
            "state": {
              "type": "file-explorer",
              "state": {
                "sortOrder": "alphabetical",
                "autoReveal": false
              },
              "icon": "lucide-folder-closed",
              "title": "文件列表"
            }
          },
          {
            "id": "3b4af9cbdca55ae8",
            "type": "leaf",
            "state": {
              "type": "search",
              "state": {
                "query": "",
                "matchingCase": false,
                "explainSearch": false,
                "collapseAll": false,
                "extraContext": false,
                "sortOrder": "alphabetical"
              },
              "icon": "lucide-search",
              "title": "搜索"
            }
          },
          {
            "id": "012f8f1c7cb3affd",
            "type": "leaf",
            "state": {
              "type": "bookmarks",
              "state": {},
              "icon": "lucide-bookmark",
              "title": "书签"
            }
          }
        ]
      }
    ],
    "direction": "horizontal",
    "width": 300
  },
  "right": {
    "id": "dc0be95d815429ed",
    "type": "split",
    "children": [
      {
        "id": "b67a8fb24e9a0df3",
        "type": "tabs",
        "children": [
          {
            "id": "1492d527e766529b",
            "type": "leaf",
            "state": {
              "type": "backlink",
              "state": {
                "file": "概念/技术概念/区块链/简介.md",
                "collapseAll": false,
                "extraContext": false,
                "sortOrder": "alphabetical",
                "showSearch": false,
                "searchQuery": "",
                "backlinkCollapsed": false,
                "unlinkedCollapsed": true
              },
              "icon": "links-coming-in",
              "title": "简介 的反向链接列表"
            }
          },
          {
            "id": "4d6b8622a1b3780c",
            "type": "leaf",
            "state": {
              "type": "outgoing-link",
              "state": {
                "file": "概念/技术概念/区块链/简介.md",
                "linksCollapsed": false,
                "unlinkedCollapsed": true
              },
              "icon": "links-going-out",
              "title": "简介 的出链列表"
            }
          },
          {
            "id": "e4e6bd9a876a508b",
            "type": "leaf",
            "state": {
              "type": "tag",
              "state": {
                "sortOrder": "frequency",
                "useHierarchy": true,
                "showSearch": false,
                "searchQuery": ""
              },
              "icon": "lucide-tags",
              "title": "标签"
            }
          },
          {
            "id": "b2311181c5f24bb8",
            "type": "leaf",
            "state": {
              "type": "outline",
              "state": {
                "file": "概念/技术概念/区块链/简介.md",
                "followCursor": false,
                "showSearch": false,
                "searchQuery": ""
              },
              "icon": "lucide-list",
              "title": "简介 的大纲"
            }
          }
        ]
      }
    ],
    "direction": "horizontal",
    "width": 300,
    "collapsed": true
  },
  "left-ribbon": {
    "hiddenItems": {
      "switcher:打开快速切换": false,
      "graph:查看关系图谱": false,
      "canvas:新建白板": false,
      "daily-notes:打开/创建今天的日记": false,
      "templates:插入模板": false,
      "command-palette:打开命令面板": false,
      "darlal-switcher-plus:Open in Headings Mode": false,
      "darlal-switcher-plus:Open Symbols for the active editor": false
    }
  },
  "active": "694dc2f3cb983df4",
  "lastOpenFiles": [
    "概念/技术概念/总线.md",
    "运维相关/工具/SaltStack.md",
    "运维相关/工具",
    "运维相关/容量管理/容量规划.md",
    "概念/技术概念/SIP.md",
    "Pasted image 20250712170959.png",
    "Pasted image 20250712170930.png",
    "Pasted image 20250712170857.png",
    "运维相关/监控.md",
    "运维相关/变更管理/概念.md",
    "运维相关/部署/分级发布.md",
    "运维相关/变更管理",
    "运维相关/部署/灰度发布(金丝雀发布).md",
    "Pasted image 20250706151756.png",
    "运维相关/流量探针.md",
    "运维相关/容量管理",
    "运维相关/部署/异地多活.md",
    "运维相关/部署/蓝绿部署.md",
    "运维相关/部署/滚动更新.md",
    "运维相关/备份/温备份.md",
    "运维相关/备份/热备份.md",
    "运维相关/备份/冷备份.md",
    "概念/技术概念/区块链/简介.md"
  ]
}